honeypot/__init__.py
honeypot/apps.py
honeypot/checks.py
honeypot/decorators.py
honeypot/middleware.py
honeypot/tests.py
honeypot/templates/honeypot/honeypot_error.html
honeypot/templates/honeypot/honeypot_field.html
honeypot/templatetags/__init__.py
honeypot/templatetags/honeypot.py
django_honeypot-1.3.0.dist-info/METADATA
django_honeypot-1.3.0.dist-info/WHEEL
django_honeypot-1.3.0.dist-info/licenses/LICENSE
django_honeypot-1.3.0.dist-info/RECORD
