Metadata-Version: 2.4
Name: django-honeypot
Version: 1.3.0
Summary: Django honeypot field utilities
Author-email: jpt <dev@jpt.sh>
License-Expression: BSD-2-Clause
License-File: LICENSE
Classifier: Development Status :: 5 - Production/Stable
Classifier: Environment :: Web Environment
Classifier: Framework :: Django :: 4.2
Classifier: Framework :: Django :: 5.0
Classifier: Framework :: Django :: 5.1
Classifier: Framework :: Django :: 5.2
Classifier: Intended Audience :: Developers
Classifier: Natural Language :: English
Classifier: Operating System :: OS Independent
Requires-Python: >=3.12
Requires-Dist: django<7,>=4.2
